unetseg/__init__.py
unetseg/console/predict.py
unetseg/console/train.py
unetseg/evaluate.py
unetseg/postprocess.py
unetseg/predict.py
unetseg/train.py
unetseg/utils.py
unetseg-0.2.4.dist-info/LICENSE.txt
unetseg-0.2.4.dist-info/METADATA
unetseg-0.2.4.dist-info/WHEEL
unetseg-0.2.4.dist-info/RECORD
