Metadata-Version: 2.1
Name: unetseg
Version: 0.2.4
Summary: U-Net semantic segmentation for satellite imagery
License: Apache-2.0
Author: Damián Silvani
Author-email: munshkr@gmail.com
Requires-Python: >=3.8,<3.11
Classifier: License :: OSI Approved :: Apache Software License
Classifier: Programming Language :: Python :: 3
Classifier: Programming Language :: Python :: 3.8
Classifier: Programming Language :: Python :: 3.9
Classifier: Programming Language :: Python :: 3.10
Requires-Dist: albumentations (>=1.1.0,<2.0.0)
Requires-Dist: matplotlib (>=3.5.1,<4.0.0)
Requires-Dist: opencv-python (>=4.5.5,<5.0.0)
Requires-Dist: rasterio (>=1.3.6,<2.0.0)
Requires-Dist: scikit-image (>=0.19.2,<0.20.0)
Requires-Dist: scikit-learn (>=1.0.2,<2.0.0)
Requires-Dist: tensorflow (>=2.4)
Requires-Dist: tifffile (>=2022.2.9,<2023.0.0)
Requires-Dist: tqdm (>=4.62.3,<5.0.0)
